strapup/__init__.py
strapup/logger.py
strapup/pystrap.py
strapup-1.0.2.dist-info/LICENSE.txt
strapup-1.0.2.dist-info/METADATA
strapup-1.0.2.dist-info/WHEEL
strapup-1.0.2.dist-info/RECORD
